Scrapy_Httpproxy-0.0.5.dist-info/METADATA
Scrapy_Httpproxy-0.0.5.dist-info/RECORD
Scrapy_Httpproxy-0.0.5.dist-info/WHEEL
Scrapy_Httpproxy-0.0.5.dist-info/top_level.txt
scrapy_httpproxy/VERSION
scrapy_httpproxy/__init__.py
scrapy_httpproxy/downloadermiddlewares/__init__.py
scrapy_httpproxy/downloadermiddlewares/httpproxy.py
scrapy_httpproxy/settings/__init__.py
scrapy_httpproxy/settings/default_settings.py
scrapy_httpproxy/storage/__init__.py
scrapy_httpproxy/storage/environment.py
scrapy_httpproxy/storage/settings.py
